flask_navigation/__init__.py
flask_navigation/api.py
flask_navigation/item.py
flask_navigation/navbar.py
flask_navigation/signals.py
flask_navigation/utils.py
Flask_Navigation-0.2.0.dist-info/DESCRIPTION.rst
Flask_Navigation-0.2.0.dist-info/METADATA
Flask_Navigation-0.2.0.dist-info/metadata.json
Flask_Navigation-0.2.0.dist-info/RECORD
Flask_Navigation-0.2.0.dist-info/top_level.txt
Flask_Navigation-0.2.0.dist-info/WHEEL
tests/integration/__init__.py
tests/integration/app.py
tests/integration/ext.py
tests/integration/test_app.py
tests/integration/views.py
