Metadata-Version: 1.1
Name: Flask-Navigation
Version: 0.2.0
Summary: The navigation of Flask application.
Home-page: https://github.com/tonyseek/flask-navigation
Author: Jiangge Zhang
Author-email: tonyseek@gmail.com
License: MIT
Keywords: navigation,flask,navbar,nav
Platform: UNKNOWN
Classifier: Programming Language :: Python
Classifier: Programming Language :: Python :: 2.7
Classifier: Programming Language :: Python :: 3.3
Classifier: Programming Language :: Python :: 3.4
Classifier: Programming Language :: Python :: Implementation :: PyPy
Classifier: Development Status :: 3 - Alpha
Classifier: License :: OSI Approved :: MIT License
Classifier: Intended Audience :: Developers
Classifier: Operating System :: OS Independent
Classifier: Environment :: Web Environment
Classifier: Framework :: Flask
Classifier: Topic :: Software Development :: Libraries :: Python Modules
